dynnode2vec/__init__.py
dynnode2vec/biased_random_walk.py
dynnode2vec/dynnode2vec.py
dynnode2vec/utils.py
dynnode2vec-0.3.1.dist-info/LICENSE
dynnode2vec-0.3.1.dist-info/WHEEL
dynnode2vec-0.3.1.dist-info/METADATA
dynnode2vec-0.3.1.dist-info/RECORD
