Metadata-Version: 2.1
Name: dynnode2vec
Version: 0.3.1
Summary: dynnode2vec is a package to embed dynamic graphs
Home-page: https://github.com/pedugnat/dynnode2vec
License: MIT
Author: pedugnat
Author-email:  
Requires-Python: >=3.8,<3.9.0
Classifier: Development Status :: 3 - Alpha
Classifier: Intended Audience :: Developers
Classifier: License :: OSI Approved :: MIT License
Classifier: Operating System :: OS Independent
Classifier: Programming Language :: Python :: 3
Classifier: Programming Language :: Python :: 3.8
Classifier: Programming Language :: Python :: 3.9
Classifier: Topic :: Software Development :: Libraries :: Python Modules
Requires-Dist: chardet (>=5.0.0,<6.0.0)
Requires-Dist: gensim (>=4.2.0,<5.0.0)
Requires-Dist: networkx (>=2.8.5,<3.0.0)
Requires-Dist: numpy (>=1.23.1,<2.0.0)
Project-URL: Repository, https://github.com/pedugnat/dynnode2vec
